kryptools/GF2.py
kryptools/Zmod.py
kryptools/__init__.py
kryptools/aes.py
kryptools/blockcipher.py
kryptools/code.py
kryptools/conway_polynomials.py
kryptools/des.py
kryptools/dlp.py
kryptools/dlp_bsgs.py
kryptools/dlp_ic.py
kryptools/dlp_qs.py
kryptools/dlp_rho.py
kryptools/ec.py
kryptools/factor.py
kryptools/factor_dix.py
kryptools/factor_ecm.py
kryptools/factor_fmt.py
kryptools/factor_pm1.py
kryptools/factor_qs.py
kryptools/factor_rho.py
kryptools/intfuncs.py
kryptools/keccak.py
kryptools/la.py
kryptools/lat.py
kryptools/lat2.py
kryptools/nt.py
kryptools/poly.py
kryptools/primes.py
kryptools/sha1.py
kryptools-1.9.1.dist-info/licenses/LICENSE
kryptools-1.9.1.dist-info/METADATA
kryptools-1.9.1.dist-info/WHEEL
kryptools-1.9.1.dist-info/top_level.txt
kryptools-1.9.1.dist-info/RECORD
