Metadata-Version: 2.4
Name: kryptools
Version: 1.9.1
Summary: Implemenation of same basic algorithms used in cryptography.
Author-email: Gerald Teschl <gerald.teschl@univie.ac.at>
License: MIT
Project-URL: Homepage, https://github.com/teschlg/kryptools
Project-URL: Source, https://github.com/teschlg/kryptools
Project-URL: Issues, https://github.com/teschlg/kryptools/issues
Project-URL: Docs, https://github.com/teschlg/kryptools/tree/main/doc
Classifier: Programming Language :: Python :: 3
Classifier: License :: OSI Approved :: MIT License
Classifier: Operating System :: OS Independent
Requires-Python: >=3.10
License-File: LICENSE
Dynamic: license-file
